ruff_severity_changer/__init__.py
ruff_severity_changer/ruff_severity_changer.py
ruff_severity_changer-0.1.4.dist-info/METADATA
ruff_severity_changer-0.1.4.dist-info/WHEEL
ruff_severity_changer-0.1.4.dist-info/entry_points.txt
ruff_severity_changer-0.1.4.dist-info/licenses/LICENSE
ruff_severity_changer-0.1.4.dist-info/RECORD
