Metadata-Version: 2.4
Name: ruff-severity-changer
Version: 0.1.4
Summary: Script modifying severity in Ruff code quality reports
Project-URL: Repository, https://gitlab.com/cammiesoft/ruff-severity-changer
Project-URL: Issues, https://gitlab.com/cammiesoft/ruff-severity-changer/-/issues
Author-email: OokamiTheLord <kuba@axod.pl>
License: # GNU GENERAL PUBLIC LICENSE
License-File: LICENSE
Classifier: Development Status :: 4 - Beta
Classifier: License :: OSI Approved :: GNU General Public License v3 or later (GPLv3+)
Classifier: Operating System :: OS Independent
Classifier: Programming Language :: Python :: 3
Requires-Python: >=3.8
